<?xml version="1.0" encoding="UTF-8"?>
<entry xmlns="http://www.w3.org/2005/Atom" xmlns:dcterms="http://purl.org/dc/terms" xmlns:xhtml="http://www.w3.org/1999/xhtml">
  <title>¿Y si te toco yo?</title>
  <id>urn:book:2b2f34ca-6856-4a40-bdbc-3db50106dafd</id>
  <updated>2023-01-26T07:16:20Z</updated>
  <link href="./book_183.xml" type="application/atom+xml;type=entry;profile=opds-catalog" rel="self" title="¿Y si te toco yo?" />
  <link href="../index.xml" type="application/atom+xml;profile=opds-catalog;kind=navigation" rel="start" title="LIBURUAK" />
  <link href="../index.xml" type="application/atom+xml;profile=opds-catalog;kind=navigation" rel="breadcrumb" title="LIBURUAK" />
  <link href="../authorlist/authorlist_Page_1.xml" type="application/atom+xml;profile=opds-catalog;kind=navigation" rel="breadcrumb" title="Autores" />
  <link href="../authorlist/authorlist_C_Page_1.xml" type="application/atom+xml;profile=opds-catalog;kind=navigation" rel="breadcrumb" title="Autores que empiezan por C" />
  <link href="../authorlist/authorlist_C_Page_2.xml" type="application/atom+xml;profile=opds-catalog;kind=navigation" rel="breadcrumb" title="Autores que empiezan por C" />
  <link href="../authorlist/authorlist_C_Page_3.xml" type="application/atom+xml;profile=opds-catalog;kind=navigation" rel="breadcrumb" title="Autores que empiezan por C" />
  <link href="../authorlist/authorlist_C_Page_4.xml" type="application/atom+xml;profile=opds-catalog;kind=navigation" rel="breadcrumb" title="Autores que empiezan por C" />
  <link href="../authorlist/authorlist_C_Page_5.xml" type="application/atom+xml;profile=opds-catalog;kind=navigation" rel="breadcrumb" title="Autores que empiezan por C" />
  <link href="../authorlist/authorlist_C_Page_6.xml" type="application/atom+xml;profile=opds-catalog;kind=navigation" rel="breadcrumb" title="Autores que empiezan por C" />
  <link href="../../Chloe%20Collins/_Y%20si%20te%20toco%20yo_%20%28183%29/c2o_resizedcover.jpg" type="image/jpg" rel="http://opds-spec.org/image" />
  <link href="../../Chloe%20Collins/_Y%20si%20te%20toco%20yo_%20%28183%29/c2o_thumbnail.jpg" type="image/jpg" rel="http://opds-spec.org/image/thumbnail" />
  <link href="../../Chloe%20Collins/_Y%20si%20te%20toco%20yo_%20%28183%29/_Y%20si%20te%20toco%20yo_%20-%20Chloe%20Collins.epub" type="application/epub+zip" rel="http://opds-spec.org/acquisition" title="Descargar este libro como EPUB" displaysize="637 KB" />
  <author>
    <name>Chloe Collins</name>
    <uri>../authors_0/authors_120_Page_1.xml</uri>
  </author>
  <published>2022-08-01T10:00:00Z</published>
  <dcterms:language>es</dcterms:language>
  <dcterms:publisher>Zafiro eBooks</dcterms:publisher>
  <category term="Romántica" />
  <category term="Lang:es" />
  <content type="text/html">
    <p>
      <strong>Rating:</strong>
      Sin puntuación
    </p>
    <p>
      <strong>Etiquetas:</strong>
      Romántica, Lang:es
    </p>
    <p>
      <strong>Sumario:</strong>
    </p>
    <p xmlns="" align="justify">Berta es una joven sevillana graduada en
    Química que se traslada a Madrid con la intención de
    «comerse el mundo», pero lo único que consigue
    zamparse son los dónuts, a poder ser de chocolate, que son
    sus preferidos...</p>
    <br xmlns="" align="justify" />
    <br xmlns="" />
    <p xmlns="" align="justify">Su impuntualidad y su falta de tacto cada
    vez que abre la boca han provocado que la despidan de varios
    trabajos que nada tienen que ver con su carrera. Su única
    opción es que le toque la lotería, en la que suele
    gastarse el poco dinero que tiene pretendiendo ser una de las
    grandes afortunadas del día.</p>
    <br xmlns="" align="justify" />
    <br xmlns="" />
    <p xmlns="" align="justify">Cuando piensa que todo está perdido, el
    destino hace de las suyas para que su suerte cambie y aparezca
    Roberto, la última esperanza para poder encauzar su
    vida.</p>
    <br xmlns="" align="justify" />
    <br xmlns="" />
    <p xmlns="" align="justify">¿Te apetece conocer a Berta? Te invito
    a que te adentres en esta historia y la descubras. Te garantizo
    que pasaremos unas horas divertidas y disparatadas en las que,
    sin duda, te haré desconectar de la rutina.</p>
  </content>
  <link href="../authors_0/authors_120_Page_1.xml" type="application/atom+xml;profile=opds-catalog;kind=navigation" rel="related" title="Libros de Chloe Collins" />
</entry>
