<?xml version="1.0" encoding="UTF-8"?>
<entry xmlns="http://www.w3.org/2005/Atom" xmlns:dcterms="http://purl.org/dc/terms" xmlns:xhtml="http://www.w3.org/1999/xhtml">
  <title>La pareja de al lado</title>
  <id>urn:book:00d35178-2ff6-4b28-9f87-4793634a8321</id>
  <updated>2023-05-15T05:51:28Z</updated>
  <link href="./book_673.xml" type="application/atom+xml;type=entry;profile=opds-catalog" rel="self" title="La pareja de al lado" />
  <link href="../index.xml" type="application/atom+xml;profile=opds-catalog;kind=navigation" rel="start" title="LIBURUAK" />
  <link href="../index.xml" type="application/atom+xml;profile=opds-catalog;kind=navigation" rel="breadcrumb" title="LIBURUAK" />
  <link href="../authorlist/authorlist_Page_1.xml" type="application/atom+xml;profile=opds-catalog;kind=navigation" rel="breadcrumb" title="Autores" />
  <link href="../authorlist/authorlist_L_Page_1.xml" type="application/atom+xml;profile=opds-catalog;kind=navigation" rel="breadcrumb" title="Autores que empiezan por L" />
  <link href="../../Shari%20Lapena/La%20pareja%20de%20al%20lado%20%28673%29/c2o_resizedcover.jpg" type="image/jpg" rel="http://opds-spec.org/image" />
  <link href="../../Shari%20Lapena/La%20pareja%20de%20al%20lado%20%28673%29/c2o_thumbnail.jpg" type="image/jpg" rel="http://opds-spec.org/image/thumbnail" />
  <link href="../../Shari%20Lapena/La%20pareja%20de%20al%20lado%20%28673%29/La%20pareja%20de%20al%20lado%20-%20Shari%20Lapena.epub" type="application/epub+zip" rel="http://opds-spec.org/acquisition" title="Descargar este libro como EPUB" displaysize="617 KB" />
  <author>
    <name>Shari Lapena</name>
    <uri>../authors_0/authors_500_Page_1.xml</uri>
  </author>
  <published>2017-01-11T11:00:00Z</published>
  <dcterms:language>es</dcterms:language>
  <dcterms:publisher>Suma de Letras</dcterms:publisher>
  <category term="Lang:es" />
  <content type="text/html">
    <p>
      <strong>Rating:</strong>
      Sin puntuación
    </p>
    <p>
      <strong>Etiquetas:</strong>
      Lang:es
    </p>
    <p>
      <strong>Sumario:</strong>
    </p>
    <div xmlns="" aria-expanded="true" class="a-expander-content a-expander-partial-collapse-content a-expander-content-expanded" style="padding-bottom: 20px;">
      <p>Todo comenzó en una cena con los vecinos...</p>
      <p>
        <span class="a-text-bold a-text-italic">La pareja de al
      lado</span>
        <span class="a-text-bold">: «El</span>
        <span class="a-text-bold a-text-italic">thriller</span>
        <span class="a-text-bold">del que todo el mundo habla».
      (</span>
        <span class="a-text-bold a-text-italic">Stylist</span>
        )
      </p>
      <p>
        <span class="a-text-bold">Libro del año para WH Smith en
      Gran Bretaña.</span>
        <br />
        <span class="a-text-bold">En la lista de más
      vendidosdurante semanas de</span>
        <span class="a-text-bold a-text-italic">The New York
      Times.</span>
        <br />
        <span class="a-text-bold">Número 1 en más
      vendidosen Canadá.</span>
        <br />
        <span class="a-text-bold">En la lista de más vendidos
      de</span>
        <span class="a-text-bold a-text-italic">The Sunday
      Times.</span>
        <br />
        <span class="a-text-bold">Uno de los mejores libros de 2016
      para</span>
        <span class="a-text-bold a-text-italic">The Globe.</span>
        <br />
        <span class="a-text-bold">Finalista de los Premios Goodreads
      2016.</span>
      </p>
      <p>Tu vecina te dijo que preferiría que no llevaras a tu
      bebé de seis meses a la cena. No es nada personal,
      simplemente no soporta sus llantos.</p>
      <p>Tu marido estaba de acuerdo. Después de todo,
      vivís en la casa de al lado. Podíais llevaros el
      monitor infantil y turnaros para pasar a verla cada media
      hora.</p>
      <p>Tu hija dormía cuando fuiste a comprobar por
      última vez. Sin embargo, en este momento, mientras subes
      corriendo las escaleras hasta su habitación envuelta en
      un absoluto silencio, confirmas que tu peor pesadilla se ha
      hecho realidad: ha desaparecido.</p>
      <p>Nunca antes habías tenido que llamar a la
      policía. Ahora están en tu casa y quién sabe
      lo que pueden llegar a descubrir.</p>
      <p>
        <span class="a-text-bold">¿De qué serías
        capaz cuando has sobrepasado tus límites?</span>
      </p>
      <p>
        <span class="a-text-bold">Críticas:</span>
        <br />
        «Alta tensión que se mantiene hasta la
      última, y asombrosa, página».
        <br />
        <span class="a-text-italic">The Times</span>
      </p>
      <p>
        «Un
        <span class="a-text-italic">thriller</span>
        psicológico
      potente, nada sanguinario, muy visual y atractivo. Una novela
      que entusiasmará: fresca, dinámica, bien aparejada,
      cautivadora desde la primera página».
        <br />
        <span class="a-text-italic">El Periódico de
      Catalunya</span>
      </p>
      <p>
        «Un debut demoledor y lleno de suspense».
        <br />
        <span class="a-text-italic">Publishers Weekly</span>
      </p>
      <p>
        «Por completo fascinante, totalmente realista y
      contado con un estilo maravillosamente sencillo y efectivo.
      No verás venir las sorpresas».
        <br />
        <span class="a-text-italic">Daily Mail</span>
      </p>
      <p>
        «Unarranque impactante para un
        <span class="a-text-italic">thriller</span>
        ejecutado con
      maestría, lleno de giros y repleto de culpa, drama y
      engaño».
        <br />
        <span class="a-text-italic">Sunday Mirror</span>
      </p>
      <p>
        «Una lectura que te atrapa con una trama que te
      hará pasar las páginas a toda velocidad para
      averiguar qué es lo siguiente que va a pasar.»
        <br />
        <span class="a-text-italic">Grazia</span>
      </p>
      <p>
        «¡¿Dónde está el bebé?! Es
      difícil no dejar de leer hasta el final para
      averiguarlo, y los giros que te aguardan allí son
      gratamente inteligentes.»
        <br />
        <span class="a-text-italic">USA Today</span>
      </p>
      <p>
        «Un lujo de
        <span class="a-text-italic">thriller</span>
        que avanza a un
      ritmo de vértigo.»
        <br />
        <span class="a-text-italic">Good Housekeeping</span>
      </p>
      <p>
        «Lleno de suspense... Los giros se van revelando
      sutilmente y con gran aplomo, llevando a la historia a
      niveles cada vez más altos de impredecibilidad.»
        <br />
        <span class="a-text-italic">Associated Press</span>
      </p>
      <p>
        <span class="a-text-bold">Los lectores han dicho...</span>
        <br />
        «El libro perfecto para amantes del suspense y la
      novela policiaca.»
        <br />
        Blog
        <span class="a-text-italic">Nadando entre palabras</span>
      </p>
      <p>
        «Un
        <span class="a-text-italic">thriller</span>
        adictivo que
      hará con tu mente y tus teorías una bola, las
      enredará y desenredará a su antojo, y no contento
      con ello, cuando creas saberlo todo, ¡pum! Nada era lo
      que parecía... Vais a alucinar.»
        <br />
        Blog
        <span class="a-text-italic">El primer
      capítulo</span>
      </p>
      <p>
        «Atrapa al lector en una atmósfera angustiosa e
      inquietante y en una lectura frenética... Una historia
      que se lee vorazmente, que nos atrapa por su ágil ritmo
      y que termina con un sorprendente final.»
        <br />
        Blog
        <span class="a-text-italic">El templo de la
      lectura</span>
      </p>
    </div>
  </content>
  <link href="../authors_0/authors_500_Page_1.xml" type="application/atom+xml;profile=opds-catalog;kind=navigation" rel="related" title="Libros de Shari Lapena" />
</entry>
