<?xml version="1.0" encoding="UTF-8"?>
<entry xmlns="http://www.w3.org/2005/Atom" xmlns:dcterms="http://purl.org/dc/terms" xmlns:xhtml="http://www.w3.org/1999/xhtml">
  <title>Tango del torturador arrepentido</title>
  <id>urn:book:241a0367-615e-44bb-a4dc-ed514b5c389a</id>
  <updated>2024-05-22T06:46:46Z</updated>
  <link href="./book_1516.xml" type="application/atom+xml;type=entry;profile=opds-catalog" rel="self" title="Tango del torturador arrepentido" />
  <link href="../index.xml" type="application/atom+xml;profile=opds-catalog;kind=navigation" rel="start" title="LIBURUAK" />
  <link href="../index.xml" type="application/atom+xml;profile=opds-catalog;kind=navigation" rel="breadcrumb" title="LIBURUAK" />
  <link href="../authorlist/authorlist_Page_1.xml" type="application/atom+xml;profile=opds-catalog;kind=navigation" rel="breadcrumb" title="Autores" />
  <link href="../authorlist/authorlist_S_Page_1.xml" type="application/atom+xml;profile=opds-catalog;kind=navigation" rel="breadcrumb" title="Autores que empiezan por S" />
  <link href="../../Carlos%20Salem/Tango%20del%20torturador%20arrepentido%20%281516%29/c2o_resizedcover.jpg" type="image/jpg" rel="http://opds-spec.org/image" />
  <link href="../../Carlos%20Salem/Tango%20del%20torturador%20arrepentido%20%281516%29/c2o_thumbnail.jpg" type="image/jpg" rel="http://opds-spec.org/image/thumbnail" />
  <link href="../../Carlos%20Salem/Tango%20del%20torturador%20arrepentido%20%281516%29/Tango%20del%20torturador%20arrepentid%20-%20Carlos%20Salem.epub" type="application/epub+zip" rel="http://opds-spec.org/acquisition" title="Descargar este libro como EPUB" displaysize="505 KB" />
  <author>
    <name>Carlos Salem</name>
    <uri>../authors_0/authors_715_Page_1.xml</uri>
  </author>
  <published>2024-04-22T00:00:00Z</published>
  <dcterms:language>es</dcterms:language>
  <dcterms:publisher>Editorial Alrevés</dcterms:publisher>
  <category term="Lang:es" />
  <content type="text/html">
    <p>
      <strong>Rating:</strong>
      Sin puntuación
    </p>
    <p>
      <strong>Etiquetas:</strong>
      Lang:es
    </p>
    <p>
      <strong>Sumario:</strong>
    </p>
    <div xmlns="" data-expanded="false" class="a-expander-content a-expander-partial-collapse-content">
      <p>
        <span class="a-text-bold">Buenos Aires, 1978.</span>
        A dos
      años del
        <span class="a-text-bold">golpe de Estado</span>
        , miles de
      personas son recluidas en centros clandestinos de
      detención. La mayoría no saldrá con vida.
      Julio, joven hijo de un poderoso industrial, es uno de ellos,
      un «
        <span class="a-text-bold">desaparecido</span>
        » más.
      Salvará su vida el mayor Morales, a cargo del cuartel,
      porque le recuerda a su hijo fallecido en un accidente. Tres
      meses más tarde, Julio es «liberado», pero ya
      no será el mismo. Ha tomado una decisión.
      </p>
      <p>
        <span class="a-text-bold">Madrid, 2000</span>
        . Julio se llama
      ahora Jorge Luis. Lleva una vida acomodada y solitaria.
      Durante una salida fortuita, se encuentra con Morales y
      despierta en él la voz de Julio, que exige venganza. Se
      introduce en la vida del exmilitar para destruirlo, y
      desarrolla hacia el hombre que debe matar un afecto que no
      tuvo por su propio padre. 
      </p>
      <p>Pero la historia de ambos es una canción triste, un
      tango fatal del que ya suenan los compases finales.</p>
    </div>
  </content>
  <link href="../authors_0/authors_715_Page_1.xml" type="application/atom+xml;profile=opds-catalog;kind=navigation" rel="related" title="Libros de Carlos Salem" />
</entry>
